pylytic/__init__.py
pylytic/extras.py
pylytic/storage.py
pylytic/__pycache__/__init__.cpython-312.pyc
pylytic/__pycache__/extras.cpython-312.pyc
pylytic/__pycache__/storage.cpython-312.pyc
pylytic/evaluation/__init__.py
pylytic/evaluation/eval.py
pylytic/evaluation/__pycache__/__init__.cpython-312.pyc
pylytic/evaluation/__pycache__/eval.cpython-312.pyc
pylytic/math_methods/__init__.py
pylytic/math_methods/m_eval.py
pylytic/math_methods/__pycache__/__init__.cpython-312.pyc
pylytic/math_methods/__pycache__/m_eval.cpython-312.pyc
pylytic-0.2.0.dist-info/METADATA
pylytic-0.2.0.dist-info/WHEEL
pylytic-0.2.0.dist-info/top_level.txt
pylytic-0.2.0.dist-info/RECORD
